tests/__init__.py
tests/test_client.py
tests/test_exceptions.py
tests/test_types.py
ai_img_gen_python-0.1.4.post20250314132522.dist-info/LICENSE
ai_img_gen_python-0.1.4.post20250314132522.dist-info/METADATA
ai_img_gen_python-0.1.4.post20250314132522.dist-info/WHEEL
ai_img_gen_python-0.1.4.post20250314132522.dist-info/top_level.txt
ai_img_gen_python-0.1.4.post20250314132522.dist-info/RECORD
